scop_solver_trial/__init__.py
scop_solver_trial/py.typed
scop_solver_trial/scop-linux
scop_solver_trial/scop-mac
scop_solver_trial/scop-win.exe
scop_solver_trial/scop.py
scop_solver_trial-0.1.1.dist-info/METADATA
scop_solver_trial-0.1.1.dist-info/WHEEL
scop_solver_trial-0.1.1.dist-info/licenses/LICENSE
scop_solver_trial-0.1.1.dist-info/RECORD
