Metadata-Version: 2.3
Name: scop-solver-trial
Version: 0.1.1
Summary: Scop trial version.
Author-email: Mikio Kubo <kubo@kaiyodai.ac.jp>, Saito Tsutomu <tsutomu7@hotmail.co.jp>
License: Apache-2.0
Requires-Python: >=3.10
Requires-Dist: plotly>=5.24.1
